crypt4gh/__init__.py
crypt4gh/__main__.py
crypt4gh/cli.py
crypt4gh/debug.py
crypt4gh/exceptions.py
crypt4gh/header.py
crypt4gh/lib.py
crypt4gh/keys/__init__.py
crypt4gh/keys/__main__.py
crypt4gh/keys/c4gh.py
crypt4gh/keys/debug.py
crypt4gh/keys/kdf.py
crypt4gh/keys/ssh.py
crypt4gh-1.7.dist-info/LICENSE
crypt4gh-1.7.dist-info/METADATA
crypt4gh-1.7.dist-info/WHEEL
crypt4gh-1.7.dist-info/entry_points.txt
crypt4gh-1.7.dist-info/top_level.txt
crypt4gh-1.7.dist-info/RECORD
