Metadata-Version: 2.1
Name: crypt4gh
Version: 1.7
Summary: GA4GH cryptographic utilities
Home-page: https://www.github.com/EGA-archive/crypt4gh
Author: Frédéric Haziza
Author-email: frederic.haziza@crg.eu
License: Apache License 2.0
Platform: any
Classifier: Development Status :: 5 - Production/Stable
Classifier: License :: OSI Approved :: Apache Software License
Classifier: Natural Language :: English
Classifier: Operating System :: MacOS :: MacOS X
Classifier: Operating System :: POSIX
Classifier: Operating System :: POSIX :: BSD
Classifier: Operating System :: POSIX :: Linux
Classifier: Intended Audience :: Developers
Classifier: Intended Audience :: Healthcare Industry
Classifier: Intended Audience :: Information Technology
Classifier: Topic :: Security :: Cryptography
Classifier: Topic :: Scientific/Engineering :: Bio-Informatics
Classifier: Programming Language :: Python :: 3.6
Classifier: Programming Language :: Python :: 3.7
Classifier: Programming Language :: Python :: 3.8
Classifier: Programming Language :: Python :: Implementation :: CPython
Requires-Python: >=3.6
License-File: LICENSE
Requires-Dist: pyYaml >=5.1.2
Requires-Dist: docopt
Requires-Dist: cryptography >=2.8
Requires-Dist: pynacl >=1.3.0
Requires-Dist: bcrypt
